{
"type": "FeatureCollection",
"crs": { "type": "name", "properties": { "name": "urn:ogc:def:crs:OGC:1.3:CRS84" } },
"features": [
{ "type": "Feature", "properties": { "OBJECTID": 10, "DISTRICT": 10, "REP": "AMANDA MAYS BLEDSOE", "URL": "http:\/\/www.lexingtonky.gov\/council-district-10", "TELEPHONE": "(859) 425-2285", "EMAIL": "abledsoe@lexingtonky.gov", "last_edite": null, "SHAPE_Leng": 97950.834670900003, "SHAPE_Area": 192151778.96399999 }, "geometry": { "type": "Point", "coordinates": [ -84.558982576530909, 38.009909688247014 ] } }
]
}
